{
  "name": "Dissonance App Repo",
  "identifier": "io.github.dissonance.repo",
  "iconURL": "https://dissonance.github.io/assets/icon-altstore.png",
  "apps": [
    {
      "name": "Dissonance",
      "bundleIdentifier": "com.hammerandchisel.discord",
      "developerName": "Pylix",
      "iconURL": "https://dissonance.github.io/assets/icon-altstore.png",
      "localizedDescription": "A client mod for Discord",
      "subtitle": "A client mod for Discord",
      "tintColor": "7289da",
      "versions": [],
      "appPermissions": {}
    },
    {
      "name": "Dissonance (TestFlight)",
      "bundleIdentifier": "com.hammerandchisel.discord.testflight",
      "developerName": "Pylix",
      "iconURL": "https://dissonance.github.io/assets/icon-altstore.png",
      "localizedDescription": "A client mod for Discord (TestFlight builds)",
      "subtitle": "A client mod for Discord (TestFlight)",
      "tintColor": "7289da",
      "versions": [],
      "appPermissions": {}
    }
  ],
  "news": []
}
